{"v":"4.8.0","meta":{"g":"LottieFiles AE 1.1.0","a":"","k":"","d":"","tc":""},"fr":29.9700012207031,"ip":0,"op":30.0000012219251,"w":600,"h":600,"nm":"section5","ddd":0,"assets":[{"id":"comp_0","layers":[{"ddd":0,"ind":1,"ty":4,"nm":"base 12","sr":1,"ks":{"o":{"a":0,"k":100,"ix":11},"r":{"a":0,"k":0,"ix":10},"p":{"a":0,"k":[231.675,397.676,0],"ix":2},"a":{"a":0,"k":[0,0,0],"ix":1},"s":{"a":0,"k":[100,100,100],"ix":6}},"ao":0,"shapes":[{"ty":"gr","it":[{"ind":0,"ty":"sh","ix":1,"ks":{"a":0,"k":{"i":[[0,0],[2.579,0],[0,-2.584],[0,0],[-2.579,0],[0,2.585]],"o":[[0,-2.584],[-2.579,0],[0,0],[0,2.585],[2.579,0],[0,0]],"v":[[4.669,-0.098],[0,-4.779],[-4.669,-0.098],[-4.669,0.099],[0,4.779],[4.669,0.099]],"c":true},"ix":2},"nm":"Path 1","mn":"ADBE Vector Shape - Group","hd":false},{"ty":"fl","c":{"a":0,"k":[0.517647087574,0.752941191196,0.521568655968,1],"ix":4},"o":{"a":0,"k":100,"ix":5},"r":1,"bm":0,"nm":"Fill 1","mn":"ADBE Vector Graphic - Fill","hd":false},{"ty":"tr","p":{"a":0,"k":[0,0],"ix":2},"a":{"a":0,"k":[0,0],"ix":1},"s":{"a":0,"k":[100,100],"ix":3},"r":{"a":0,"k":0,"ix":6},"o":{"a":0,"k":100,"ix":7},"sk":{"a":0,"k":0,"ix":4},"sa":{"a":0,"k":0,"ix":5},"nm":"Transform"}],"nm":"Group 1","np":2,"cix":2,"bm":0,"ix":1,"mn":"ADBE Vector Group","hd":false}],"ip":0,"op":60.0000024438501,"st":0,"bm":0},{"ddd":0,"ind":2,"ty":4,"nm":"base 11","sr":1,"ks":{"o":{"a":0,"k":100,"ix":11},"r":{"a":0,"k":0,"ix":10},"p":{"a":0,"k":[231.675,354.32,0],"ix":2},"a":{"a":0,"k":[0,0,0],"ix":1},"s":{"a":0,"k":[100,100,100],"ix":6}},"ao":0,"shapes":[{"ty":"gr","it":[{"ind":0,"ty":"sh","ix":1,"ks":{"a":0,"k":{"i":[[0,0],[2.579,0],[0,-2.585],[0,0],[-2.579,0],[0,2.585]],"o":[[0,-2.585],[-2.579,0],[0,0],[0,2.585],[2.579,0],[0,0]],"v":[[4.669,-0.098],[0,-4.778],[-4.669,-0.098],[-4.669,0.098],[0,4.778],[4.669,0.098]],"c":true},"ix":2},"nm":"Path 1","mn":"ADBE Vector Shape - Group","hd":false},{"ty":"fl","c":{"a":0,"k":[0.517647087574,0.752941191196,0.521568655968,1],"ix":4},"o":{"a":0,"k":100,"ix":5},"r":1,"bm":0,"nm":"Fill 1","mn":"ADBE Vector Graphic - Fill","hd":false},{"ty":"tr","p":{"a":0,"k":[0,0],"ix":2},"a":{"a":0,"k":[0,0],"ix":1},"s":{"a":0,"k":[100,100],"ix":3},"r":{"a":0,"k":0,"ix":6},"o":{"a":0,"k":100,"ix":7},"sk":{"a":0,"k":0,"ix":4},"sa":{"a":0,"k":0,"ix":5},"nm":"Transform"}],"nm":"Group 1","np":2,"cix":2,"bm":0,"ix":1,"mn":"ADBE Vector Group","hd":false}],"ip":0,"op":60.0000024438501,"st":0,"bm":0},{"ddd":0,"ind":3,"ty":4,"nm":"base 10","sr":1,"ks":{"o":{"a":0,"k":100,"ix":11},"r":{"a":0,"k":0,"ix":10},"p":{"a":0,"k":[231.675,310.951,0],"ix":2},"a":{"a":0,"k":[0,0,0],"ix":1},"s":{"a":0,"k":[100,100,100],"ix":6}},"ao":0,"shapes":[{"ty":"gr","it":[{"ind":0,"ty":"sh","ix":1,"ks":{"a":0,"k":{"i":[[0,0],[2.579,0],[0,-2.585],[0,0],[-2.579,0],[0,2.584]],"o":[[0,-2.585],[-2.579,0],[0,0],[0,2.584],[2.579,0],[0,0]],"v":[[4.669,-0.098],[0,-4.779],[-4.669,-0.098],[-4.669,0.098],[0,4.779],[4.669,0.098]],"c":true},"ix":2},"nm":"Path 1","mn":"ADBE Vector Shape - Group","hd":false},{"ty":"fl","c":{"a":0,"k":[0.517647087574,0.752941191196,0.521568655968,1],"ix":4},"o":{"a":0,"k":100,"ix":5},"r":1,"bm":0,"nm":"Fill 1","mn":"ADBE Vector Graphic - Fill","hd":false},{"ty":"tr","p":{"a":0,"k":[0,0],"ix":2},"a":{"a":0,"k":[0,0],"ix":1},"s":{"a":0,"k":[100,100],"ix":3},"r":{"a":0,"k":0,"ix":6},"o":{"a":0,"k":100,"ix":7},"sk":{"a":0,"k":0,"ix":4},"sa":{"a":0,"k":0,"ix":5},"nm":"Transform"}],"nm":"Group 1","np":2,"cix":2,"bm":0,"ix":1,"mn":"ADBE Vector Group","hd":false}],"ip":0,"op":60.0000024438501,"st":0,"bm":0},{"ddd":0,"ind":4,"ty":4,"nm":"base 9","sr":1,"ks":{"o":{"a":0,"k":100,"ix":11},"r":{"a":0,"k":0,"ix":10},"p":{"a":0,"k":[282.843,224.022,0],"ix":2},"a":{"a":0,"k":[0,0,0],"ix":1},"s":{"a":0,"k":[100,100,100],"ix":6}},"ao":0,"shapes":[{"ty":"gr","it":[{"ind":0,"ty":"sh","ix":1,"ks":{"a":0,"k":{"i":[[0,0],[2.579,0],[0,-2.585],[0,0],[-2.578,0],[0,2.585]],"o":[[0,-2.585],[-2.578,0],[0,0],[0,2.585],[2.579,0],[0,0]],"v":[[4.67,-0.098],[0,-4.779],[-4.67,-0.098],[-4.67,0.098],[0,4.779],[4.67,0.098]],"c":true},"ix":2},"nm":"Path 1","mn":"ADBE Vector Shape - Group","hd":false},{"ty":"fl","c":{"a":0,"k":[0.517647087574,0.752941191196,0.521568655968,1],"ix":4},"o":{"a":0,"k":100,"ix":5},"r":1,"bm":0,"nm":"Fill 1","mn":"ADBE Vector Graphic - Fill","hd":false},{"ty":"tr","p":{"a":0,"k":[0,0],"ix":2},"a":{"a":0,"k":[0,0],"ix":1},"s":{"a":0,"k":[100,100],"ix":3},"r":{"a":0,"k":0,"ix":6},"o":{"a":0,"k":100,"ix":7},"sk":{"a":0,"k":0,"ix":4},"sa":{"a":0,"k":0,"ix":5},"nm":"Transform"}],"nm":"Group 1","np":2,"cix":2,"bm":0,"ix":1,"mn":"ADBE Vector Group","hd":false}],"ip":0,"op":60.0000024438501,"st":0,"bm":0},{"ddd":0,"ind":5,"ty":4,"nm":"base 8","sr":1,"ks":{"o":{"a":0,"k":100,"ix":11},"r":{"a":0,"k":0,"ix":10},"p":{"a":0,"k":[231.675,267.582,0],"ix":2},"a":{"a":0,"k":[0,0,0],"ix":1},"s":{"a":0,"k":[100,100,100],"ix":6}},"ao":0,"shapes":[{"ty":"gr","it":[{"ind":0,"ty":"sh","ix":1,"ks":{"a":0,"k":{"i":[[0,0],[2.579,0],[0,-2.585],[0,0],[-2.579,0],[0,2.585]],"o":[[0,-2.585],[-2.579,0],[0,0],[0,2.585],[2.579,0],[0,0]],"v":[[4.669,-0.098],[0,-4.778],[-4.669,-0.098],[-4.669,0.098],[0,4.778],[4.669,0.098]],"c":true},"ix":2},"nm":"Path 1","mn":"ADBE Vector Shape - Group","hd":false},{"ty":"fl","c":{"a":0,"k":[0.517647087574,0.752941191196,0.521568655968,1],"ix":4},"o":{"a":0,"k":100,"ix":5},"r":1,"bm":0,"nm":"Fill 1","mn":"ADBE Vector Graphic - Fill","hd":false},{"ty":"tr","p":{"a":0,"k":[0,0],"ix":2},"a":{"a":0,"k":[0,0],"ix":1},"s":{"a":0,"k":[100,100],"ix":3},"r":{"a":0,"k":0,"ix":6},"o":{"a":0,"k":100,"ix":7},"sk":{"a":0,"k":0,"ix":4},"sa":{"a":0,"k":0,"ix":5},"nm":"Transform"}],"nm":"Group 1","np":2,"cix":2,"bm":0,"ix":1,"mn":"ADBE Vector Group","hd":false}],"ip":0,"op":60.0000024438501,"st":0,"bm":0},{"ddd":0,"ind":6,"ty":4,"nm":"base 7","sr":1,"ks":{"o":{"a":0,"k":100,"ix":11},"r":{"a":0,"k":0,"ix":10},"p":{"a":0,"k":[312.465,397.32,0],"ix":2},"a":{"a":0,"k":[0,0,0],"ix":1},"s":{"a":0,"k":[100,100,100],"ix":6}},"ao":0,"shapes":[{"ty":"gr","it":[{"ind":0,"ty":"sh","ix":1,"ks":{"a":0,"k":{"i":[[2.633,0],[0,0],[0,-2.636],[0,0],[-2.633,0],[0,0],[0,2.635],[0,0]],"o":[[0,0],[-2.633,0],[0,0],[0,2.635],[0,0],[2.633,0],[0,0],[0,-2.636]],"v":[[80.524,-4.779],[-80.524,-4.779],[-85.292,-0.007],[-85.292,0.007],[-80.524,4.779],[80.524,4.779],[85.292,0.007],[85.292,-0.007]],"c":true},"ix":2},"nm":"Path 1","mn":"ADBE Vector Shape - Group","hd":false},{"ty":"gf","o":{"a":0,"k":100,"ix":10},"r":1,"bm":0,"g":{"p":3,"k":{"a":0,"k":[0,0.392,0.42,0.357,0.5,0.384,0.4,0.369,1,0.376,0.38,0.38,0,1,0.5,0.5,1,0],"ix":9}},"s":{"a":0,"k":[-90.754,154.487],"ix":5},"e":{"a":0,"k":[84.327,154.487],"ix":6},"t":1,"nm":"Gradient Fill 1","mn":"ADBE Vector Graphic - G-Fill","hd":false},{"ty":"tr","p":{"a":0,"k":[0,0],"ix":2},"a":{"a":0,"k":[0,0],"ix":1},"s":{"a":0,"k":[100,100],"ix":3},"r":{"a":0,"k":0,"ix":6},"o":{"a":0,"k":100,"ix":7},"sk":{"a":0,"k":0,"ix":4},"sa":{"a":0,"k":0,"ix":5},"nm":"Transform"}],"nm":"Group 1","np":2,"cix":2,"bm":0,"ix":1,"mn":"ADBE Vector Group","hd":false}],"ip":0,"op":60.0000024438501,"st":0,"bm":0},{"ddd":0,"ind":7,"ty":4,"nm":"base 6","sr":1,"ks":{"o":{"a":0,"k":100,"ix":11},"r":{"a":0,"k":0,"ix":10},"p":{"a":0,"k":[312.297,354.32,0],"ix":2},"a":{"a":0,"k":[0,0,0],"ix":1},"s":{"a":0,"k":[100,100,100],"ix":6}},"ao":0,"shapes":[{"ty":"gr","it":[{"ind":0,"ty":"sh","ix":1,"ks":{"a":0,"k":{"i":[[2.633,0],[0,0],[0,-2.636],[0,0],[-2.633,0],[0,0],[0,2.635],[0,0]],"o":[[0,0],[-2.633,0],[0,0],[0,2.635],[0,0],[2.633,0],[0,0],[0,-2.636]],"v":[[80.524,-4.778],[-80.524,-4.778],[-85.291,-0.006],[-85.291,0.007],[-80.524,4.778],[80.524,4.778],[85.291,0.007],[85.291,-0.006]],"c":true},"ix":2},"nm":"Path 1","mn":"ADBE Vector Shape - Group","hd":false},{"ty":"gf","o":{"a":0,"k":100,"ix":10},"r":1,"bm":0,"g":{"p":3,"k":{"a":0,"k":[0,0.392,0.42,0.357,0.5,0.384,0.4,0.369,1,0.376,0.38,0.38,0,1,0.5,0.5,1,0],"ix":9}},"s":{"a":0,"k":[-90.586,68.488],"ix":5},"e":{"a":0,"k":[84.495,68.488],"ix":6},"t":1,"nm":"Gradient Fill 1","mn":"ADBE Vector Graphic - G-Fill","hd":false},{"ty":"tr","p":{"a":0,"k":[0,0],"ix":2},"a":{"a":0,"k":[0,0],"ix":1},"s":{"a":0,"k":[100,100],"ix":3},"r":{"a":0,"k":0,"ix":6},"o":{"a":0,"k":100,"ix":7},"sk":{"a":0,"k":0,"ix":4},"sa":{"a":0,"k":0,"ix":5},"nm":"Transform"}],"nm":"Group 1","np":2,"cix":2,"bm":0,"ix":1,"mn":"ADBE Vector Group","hd":false}],"ip":0,"op":60.0000024438501,"st":0,"bm":0},{"ddd":0,"ind":8,"ty":4,"nm":"base 5","sr":1,"ks":{"o":{"a":0,"k":100,"ix":11},"r":{"a":0,"k":0,"ix":10},"p":{"a":0,"k":[312.297,310.951,0],"ix":2},"a":{"a":0,"k":[0,0,0],"ix":1},"s":{"a":0,"k":[100,100,100],"ix":6}},"ao":0,"shapes":[{"ty":"gr","it":[{"ind":0,"ty":"sh","ix":1,"ks":{"a":0,"k":{"i":[[2.633,0],[0,0],[0,-2.635],[0,0],[-2.633,0],[0,0],[0,2.635],[0,0]],"o":[[0,0],[-2.633,0],[0,0],[0,2.635],[0,0],[2.633,0],[0,0],[0,-2.635]],"v":[[80.524,-4.779],[-80.524,-4.779],[-85.291,-0.007],[-85.291,0.007],[-80.524,4.779],[80.524,4.779],[85.291,0.007],[85.291,-0.007]],"c":true},"ix":2},"nm":"Path 1","mn":"ADBE Vector Shape - Group","hd":false},{"ty":"gf","o":{"a":0,"k":100,"ix":10},"r":1,"bm":0,"g":{"p":3,"k":{"a":0,"k":[0,0.392,0.42,0.357,0.5,0.384,0.4,0.369,1,0.376,0.38,0.38,0,1,0.5,0.5,1,0],"ix":9}},"s":{"a":0,"k":[-90.586,-17.882],"ix":5},"e":{"a":0,"k":[84.495,-17.882],"ix":6},"t":1,"nm":"Gradient Fill 1","mn":"ADBE Vector Graphic - G-Fill","hd":false},{"ty":"tr","p":{"a":0,"k":[0,0],"ix":2},"a":{"a":0,"k":[0,0],"ix":1},"s":{"a":0,"k":[100,100],"ix":3},"r":{"a":0,"k":0,"ix":6},"o":{"a":0,"k":100,"ix":7},"sk":{"a":0,"k":0,"ix":4},"sa":{"a":0,"k":0,"ix":5},"nm":"Transform"}],"nm":"Group 1","np":2,"cix":2,"bm":0,"ix":1,"mn":"ADBE Vector Group","hd":false}],"ip":0,"op":60.0000024438501,"st":0,"bm":0},{"ddd":0,"ind":9,"ty":4,"nm":"base 4","sr":1,"ks":{"o":{"a":0,"k":100,"ix":11},"r":{"a":0,"k":0,"ix":10},"p":{"a":0,"k":[338.308,224.231,0],"ix":2},"a":{"a":0,"k":[0,0,0],"ix":1},"s":{"a":0,"k":[100,100,100],"ix":6}},"ao":0,"shapes":[{"ty":"gr","it":[{"ind":0,"ty":"sh","ix":1,"ks":{"a":0,"k":{"i":[[1.813,0],[0,0],[0,-2.75],[0,0],[-1.813,0],[0,0],[0,2.75],[0,0]],"o":[[0,0],[-1.813,0],[0,0],[0,2.75],[0,0],[1.813,0],[0,0],[0,-2.75]],"v":[[55.447,-4.986],[-55.447,-4.986],[-58.73,-0.008],[-58.73,0.007],[-55.447,4.986],[55.447,4.986],[58.73,0.007],[58.73,-0.008]],"c":true},"ix":2},"nm":"Path 1","mn":"ADBE Vector Shape - Group","hd":false},{"ty":"gf","o":{"a":0,"k":100,"ix":10},"r":1,"bm":0,"g":{"p":3,"k":{"a":0,"k":[0,0.392,0.42,0.357,0.5,0.384,0.4,0.369,1,0.376,0.38,0.38,0,1,0.5,0.5,1,0],"ix":9}},"s":{"a":0,"k":[-62.598,-191.602],"ix":5},"e":{"a":0,"k":[57.959,-191.602],"ix":6},"t":1,"nm":"Gradient Fill 1","mn":"ADBE Vector Graphic - G-Fill","hd":false},{"ty":"tr","p":{"a":0,"k":[0,0],"ix":2},"a":{"a":0,"k":[0,0],"ix":1},"s":{"a":0,"k":[100,100],"ix":3},"r":{"a":0,"k":0,"ix":6},"o":{"a":0,"k":100,"ix":7},"sk":{"a":0,"k":0,"ix":4},"sa":{"a":0,"k":0,"ix":5},"nm":"Transform"}],"nm":"Group 1","np":2,"cix":2,"bm":0,"ix":1,"mn":"ADBE Vector Group","hd":false}],"ip":0,"op":60.0000024438501,"st":0,"bm":0},{"ddd":0,"ind":10,"ty":4,"nm":"base 3","sr":1,"ks":{"o":{"a":0,"k":100,"ix":11},"r":{"a":0,"k":0,"ix":10},"p":{"a":0,"k":[312.297,267.582,0],"ix":2},"a":{"a":0,"k":[0,0,0],"ix":1},"s":{"a":0,"k":[100,100,100],"ix":6}},"ao":0,"shapes":[{"ty":"gr","it":[{"ind":0,"ty":"sh","ix":1,"ks":{"a":0,"k":{"i":[[2.633,0],[0,0],[0,-2.635],[0,0],[-2.633,0],[0,0],[0,2.636],[0,0]],"o":[[0,0],[-2.633,0],[0,0],[0,2.636],[0,0],[2.633,0],[0,0],[0,-2.635]],"v":[[80.524,-4.778],[-80.524,-4.778],[-85.291,-0.007],[-85.291,0.006],[-80.524,4.778],[80.524,4.778],[85.291,0.006],[85.291,-0.007]],"c":true},"ix":2},"nm":"Path 1","mn":"ADBE Vector Shape - Group","hd":false},{"ty":"gf","o":{"a":0,"k":100,"ix":10},"r":1,"bm":0,"g":{"p":3,"k":{"a":0,"k":[0,0.392,0.42,0.357,0.5,0.384,0.4,0.369,1,0.376,0.38,0.38,0,1,0.5,0.5,1,0],"ix":9}},"s":{"a":0,"k":[-90.586,-105.25],"ix":5},"e":{"a":0,"k":[84.495,-105.25],"ix":6},"t":1,"nm":"Gradient Fill 1","mn":"ADBE Vector Graphic - G-Fill","hd":false},{"ty":"tr","p":{"a":0,"k":[0,0],"ix":2},"a":{"a":0,"k":[0,0],"ix":1},"s":{"a":0,"k":[100,100],"ix":3},"r":{"a":0,"k":0,"ix":6},"o":{"a":0,"k":100,"ix":7},"sk":{"a":0,"k":0,"ix":4},"sa":{"a":0,"k":0,"ix":5},"nm":"Transform"}],"nm":"Group 1","np":2,"cix":2,"bm":0,"ix":1,"mn":"ADBE Vector Group","hd":false}],"ip":0,"op":60.0000024438501,"st":0,"bm":0},{"ddd":0,"ind":11,"ty":4,"nm":"base 2","sr":1,"ks":{"o":{"a":0,"k":80,"ix":11},"r":{"a":0,"k":0,"ix":10},"p":{"a":0,"k":[357.551,455.869,0],"ix":2},"a":{"a":0,"k":[0,0,0],"ix":1},"s":{"a":0,"k":[100,100,100],"ix":6}},"ao":0,"shapes":[{"ty":"gr","it":[{"ind":0,"ty":"sh","ix":1,"ks":{"a":0,"k":{"i":[[0,0],[-6.311,6.317],[-0.13,11.978],[0,0],[7.16,-8.08],[10.879,-1.307],[0,0],[1.788,0.004],[0,0]],"o":[[8.599,-1.828],[8.472,-8.48],[0,0],[-0.118,10.788],[-7.271,8.204],[0,0],[-1.774,0.22],[0,0],[0,0]],"v":[[-119.876,22.172],[-97.003,9.744],[-83.59,-22.173],[119.876,-22.173],[108.596,7.085],[80.424,21.848],[80.422,21.848],[75.075,22.172],[75.074,22.172]],"c":true},"ix":2},"nm":"Path 1","mn":"ADBE Vector Shape - Group","hd":false},{"ty":"gs","o":{"a":0,"k":100,"ix":9},"w":{"a":0,"k":1,"ix":10},"g":{"p":3,"k":{"a":0,"k":[0,1,1,1,0.5,1,1,1,1,1,1,1,0,0.62,0.5,0.31,1,0],"ix":8}},"s":{"a":0,"k":[108.159,280.036],"ix":4},"e":{"a":0,"k":[-87.249,294.244],"ix":5},"t":1,"lc":1,"lj":1,"ml":4,"ml2":{"a":0,"k":4,"ix":13},"bm":0,"nm":"Gradient Stroke 1","mn":"ADBE Vector Graphic - G-Stroke","hd":false},{"ty":"gf","o":{"a":0,"k":100,"ix":10},"r":1,"bm":0,"g":{"p":3,"k":{"a":0,"k":[0,0.22,0.239,0.227,0.5,0.127,0.229,0.18,1,0.035,0.22,0.133,0,1,0.5,0.5,1,0],"ix":9}},"s":{"a":0,"k":[4.159,239.036],"ix":5},"e":{"a":0,"k":[-5.574,167.231],"ix":6},"t":1,"nm":"Gradient Fill 1","mn":"ADBE Vector Graphic - G-Fill","hd":false},{"ty":"tr","p":{"a":0,"k":[0,0],"ix":2},"a":{"a":0,"k":[0,0],"ix":1},"s":{"a":0,"k":[100,100],"ix":3},"r":{"a":0,"k":0,"ix":6},"o":{"a":0,"k":100,"ix":7},"sk":{"a":0,"k":0,"ix":4},"sa":{"a":0,"k":0,"ix":5},"nm":"Transform"}],"nm":"Group 1","np":3,"cix":2,"bm":0,"ix":1,"mn":"ADBE Vector Group","hd":false}],"ip":0,"op":60.0000024438501,"st":0,"bm":0},{"ddd":0,"ind":12,"ty":4,"nm":"base","sr":1,"ks":{"o":{"a":0,"k":80,"ix":11},"r":{"a":0,"k":0,"ix":10},"p":{"a":0,"k":[308.943,317.865,0],"ix":2},"a":{"a":0,"k":[0,0,0],"ix":1},"s":{"a":0,"k":[100,100,100],"ix":6}},"ao":0,"shapes":[{"ty":"gr","it":[{"ind":0,"ty":"sh","ix":1,"ks":{"a":0,"k":{"i":[[0,0],[0,0],[0,0],[8.282,-8.42],[11.709,0],[8.282,8.421],[0,11.912],[0,0],[0,0],[0,0]],"o":[[0,0],[0,0],[0,11.912],[-8.282,8.421],[-11.709,0],[-8.282,-8.42],[0,0],[0,0],[0,0],[0,0]],"v":[[-36.453,114.771],[-36.953,114.771],[-36.953,115.271],[-49.89,147.026],[-81.112,160.175],[-112.333,147.026],[-125.27,115.271],[-125.27,-160.175],[125.27,-160.175],[125.27,114.771]],"c":true},"ix":2},"nm":"Path 1","mn":"ADBE Vector Shape - Group","hd":false},{"ty":"gs","o":{"a":0,"k":100,"ix":9},"w":{"a":0,"k":1,"ix":10},"g":{"p":3,"k":{"a":0,"k":[0,1,1,1,0.5,1,1,1,1,1,1,1,0,0.62,0.5,0.31,1,0],"ix":8}},"s":{"a":0,"k":[-81.232,164.032],"ix":4},"e":{"a":0,"k":[54.623,486.271],"ix":5},"t":1,"lc":1,"lj":1,"ml":4,"ml2":{"a":0,"k":4,"ix":13},"bm":0,"nm":"Gradient Stroke 1","mn":"ADBE Vector Graphic - G-Stroke","hd":false},{"ty":"gf","o":{"a":0,"k":100,"ix":10},"r":1,"bm":0,"g":{"p":3,"k":{"a":0,"k":[0,0.22,0.239,0.227,0.5,0.127,0.229,0.18,1,0.035,0.22,0.133,0,1,0.5,0.5,1,0],"ix":9}},"s":{"a":0,"k":[106.768,-138.968],"ix":5},"e":{"a":0,"k":[-152.052,-410.322],"ix":6},"t":1,"nm":"Gradient Fill 1","mn":"ADBE Vector Graphic - G-Fill","hd":false},{"ty":"tr","p":{"a":0,"k":[0,0],"ix":2},"a":{"a":0,"k":[0,0],"ix":1},"s":{"a":0,"k":[100,100],"ix":3},"r":{"a":0,"k":0,"ix":6},"o":{"a":0,"k":100,"ix":7},"sk":{"a":0,"k":0,"ix":4},"sa":{"a":0,"k":0,"ix":5},"nm":"Transform"}],"nm":"Group 1","np":3,"cix":2,"bm":0,"ix":1,"mn":"ADBE Vector Group","hd":false}],"ip":0,"op":60.0000024438501,"st":0,"bm":0}]}],"layers":[{"ddd":0,"ind":1,"ty":4,"nm":"LOCK 2","sr":1,"ks":{"o":{"a":1,"k":[{"i":{"x":[0.833],"y":[0.833]},"o":{"x":[0.167],"y":[0.167]},"t":0,"s":[0]},{"t":30.0000012219251,"s":[100]}],"ix":11},"r":{"a":0,"k":0,"ix":10},"p":{"a":1,"k":[{"i":{"x":0.833,"y":0.833},"o":{"x":0.167,"y":0.167},"t":0,"s":[300,240,0],"to":[0,10,0],"ti":[0,-10,0]},{"t":30.0000012219251,"s":[300,300,0]}],"ix":2},"a":{"a":0,"k":[0,0,0],"ix":1},"s":{"a":0,"k":[100,100,100],"ix":6}},"ao":0,"shapes":[{"ty":"gr","it":[{"ind":0,"ty":"sh","ix":1,"ks":{"a":0,"k":{"i":[[2.849,-0.003],[1.77,1.17],[0.815,1.948],[-0.413,2.069],[-1.503,1.492],[-2.086,0.412],[-1.965,-0.807],[-1.182,-1.754],[0,-2.109],[2.014,-1.999]],"o":[[-2.127,0.002],[-1.769,-1.17],[-0.815,-1.948],[0.413,-2.069],[1.503,-1.492],[2.086,-0.412],[1.965,0.807],[1.182,1.754],[0,2.826],[-2.014,1.999]],"v":[[-105.28,-104.247],[-111.256,-106.038],[-115.221,-110.821],[-115.837,-116.982],[-112.898,-122.444],[-107.393,-125.366],[-101.18,-124.761],[-96.354,-120.834],[-94.541,-114.909],[-97.686,-107.374]],"c":true},"ix":2},"nm":"Path 1","mn":"ADBE Vector Shape - Group","hd":false},{"ind":1,"ty":"sh","ix":2,"ks":{"a":0,"k":{"i":[[0,0],[0,0],[0,0],[0,0],[0,0],[0,0],[0,0],[0,0],[0,0],[0,0],[4.151,-0.265],[2.878,-2.977],[0.092,-4.124],[-2.743,-3.101],[-4.135,-0.446],[-3.351,2.443],[-0.804,4.047],[2.166,3.522]],"o":[[0,0],[0,0],[0,0],[0,0],[0,0],[0,0],[0,0],[0,0],[0,0],[-3.239,-2.588],[-4.151,0.265],[-2.878,2.978],[-0.092,4.124],[2.743,3.101],[4.135,0.446],[3.351,-2.443],[0.804,-4.047],[0,0]],"v":[[-62.827,-151.485],[-66.847,-155.484],[-70.866,-159.459],[-74.886,-155.461],[-70.878,-151.485],[-74.734,-147.661],[-78.801,-151.636],[-82.832,-147.638],[-78.801,-143.628],[-94.786,-127.773],[-106.276,-131.385],[-117.205,-126.345],[-121.823,-115.303],[-117.701,-104.07],[-107.007,-98.556],[-95.368,-101.661],[-88.907,-111.752],[-91.024,-123.52]],"c":true},"ix":2},"nm":"Path 2","mn":"ADBE Vector Shape - Group","hd":false},{"ty":"fl","c":{"a":0,"k":[1,1,1,1],"ix":4},"o":{"a":0,"k":100,"ix":5},"r":1,"bm":0,"nm":"Fill 1","mn":"ADBE Vector Graphic - Fill","hd":false},{"ty":"tr","p":{"a":0,"k":[0,0],"ix":2},"a":{"a":0,"k":[0,0],"ix":1},"s":{"a":0,"k":[100,100],"ix":3},"r":{"a":0,"k":0,"ix":6},"o":{"a":0,"k":100,"ix":7},"sk":{"a":0,"k":0,"ix":4},"sa":{"a":0,"k":0,"ix":5},"nm":"Transform"}],"nm":"Group 1","np":3,"cix":2,"bm":0,"ix":1,"mn":"ADBE Vector Group","hd":false}],"ip":0,"op":60.0000024438501,"st":0,"bm":0},{"ddd":0,"ind":2,"ty":4,"nm":"LOCK","sr":1,"ks":{"o":{"a":1,"k":[{"i":{"x":[0.833],"y":[0.833]},"o":{"x":[0.167],"y":[0.167]},"t":0,"s":[0]},{"t":30.0000012219251,"s":[100]}],"ix":11},"r":{"a":0,"k":0,"ix":10},"p":{"a":1,"k":[{"i":{"x":0.833,"y":0.833},"o":{"x":0.167,"y":0.167},"t":0,"s":[205.173,113.041,0],"to":[0,10,0],"ti":[0,-10,0]},{"t":30.0000012219251,"s":[205.173,173.041,0]}],"ix":2},"a":{"a":0,"k":[0,0,0],"ix":1},"s":{"a":0,"k":[100,100,100],"ix":6}},"ao":0,"shapes":[{"ty":"gr","it":[{"ind":0,"ty":"sh","ix":1,"ks":{"a":0,"k":{"i":[[0,-30.932],[30.648,0],[0,30.932],[-30.648,0]],"o":[[0,30.932],[-30.648,0],[0,-30.932],[30.648,0]],"v":[[55.5,0],[0,56],[-55.5,0],[0,-56]],"c":true},"ix":2},"nm":"Path 1","mn":"ADBE Vector Shape - Group","hd":false},{"ty":"gs","o":{"a":0,"k":100,"ix":9},"w":{"a":0,"k":1,"ix":10},"g":{"p":3,"k":{"a":0,"k":[0,1,1,1,0.5,1,1,1,1,1,1,1,0,0.62,0.5,0.31,1,0],"ix":8}},"s":{"a":0,"k":[50.537,-293.791],"ix":4},"e":{"a":0,"k":[-37.534,-292.639],"ix":5},"t":1,"lc":1,"lj":1,"ml":4,"ml2":{"a":0,"k":4,"ix":13},"bm":0,"nm":"Gradient Stroke 1","mn":"ADBE Vector Graphic - G-Stroke","hd":false},{"ty":"tr","p":{"a":0,"k":[0,0],"ix":2},"a":{"a":0,"k":[0,0],"ix":1},"s":{"a":0,"k":[100,100],"ix":3},"r":{"a":0,"k":0,"ix":6},"o":{"a":0,"k":100,"ix":7},"sk":{"a":0,"k":0,"ix":4},"sa":{"a":0,"k":0,"ix":5},"nm":"Transform"}],"nm":"Group 1","np":2,"cix":2,"bm":0,"ix":1,"mn":"ADBE Vector Group","hd":false},{"ty":"gf","o":{"a":0,"k":100,"ix":10},"r":1,"bm":0,"g":{"p":3,"k":{"a":0,"k":[0,0.386,0.494,0.442,0.455,0.638,0.733,0.687,1,0.889,0.972,0.932],"ix":9}},"s":{"a":0,"k":[0,0],"ix":5},"e":{"a":0,"k":[100,0],"ix":6},"t":1,"nm":"Gradient Fill 1","mn":"ADBE Vector Graphic - G-Fill","hd":false}],"ip":0,"op":60.0000024438501,"st":0,"bm":0},{"ddd":0,"ind":3,"ty":0,"nm":"Pre-comp 2","refId":"comp_0","sr":1,"ks":{"o":{"a":1,"k":[{"i":{"x":[0.833],"y":[0.833]},"o":{"x":[0.167],"y":[0.167]},"t":0,"s":[0]},{"t":30.0000012219251,"s":[100]}],"ix":11},"r":{"a":0,"k":0,"ix":10},"p":{"a":1,"k":[{"i":{"x":0.833,"y":0.833},"o":{"x":0.167,"y":0.167},"t":0,"s":[300,380,0],"to":[0,-13.333,0],"ti":[0,13.333,0]},{"t":30.0000012219251,"s":[300,300,0]}],"ix":2},"a":{"a":0,"k":[300,300,0],"ix":1},"s":{"a":0,"k":[100,100,100],"ix":6}},"ao":0,"w":600,"h":600,"ip":0,"op":60.0000024438501,"st":0,"bm":0}],"markers":[]}